{
"meta":{"test_sets":[],"test_metrics":[],"learn_metrics":[{"best_value":"Min","name":"RMSE"}],"launch_mode":"Train","parameters":"","iteration_count":200,"learn_sets":["learn"],"name":"experiment"},
"iterations":[
{"learn":[1225.60823],"iteration":0,"passed_time":0.06262748194,"remaining_time":12.46286891},
{"learn":[1211.64567],"iteration":1,"passed_time":0.06489160689,"remaining_time":6.424269082},
{"learn":[1197.707952],"iteration":2,"passed_time":0.06648102944,"remaining_time":4.3655876},
{"learn":[1182.886057],"iteration":3,"passed_time":0.06840919911,"remaining_time":3.352050756},
{"learn":[1169.455529],"iteration":4,"passed_time":0.06970856774,"remaining_time":2.718634142},
{"learn":[1153.015317],"iteration":5,"passed_time":0.07131786134,"remaining_time":2.305944183},
{"learn":[1136.536281],"iteration":6,"passed_time":0.07250666568,"remaining_time":1.999112354},
{"learn":[1124.134381],"iteration":7,"passed_time":0.07387907191,"remaining_time":1.773097726},
{"learn":[1110.434683],"iteration":8,"passed_time":0.0751163307,"remaining_time":1.594135463},
{"learn":[1099.604288],"iteration":9,"passed_time":0.07666712495,"remaining_time":1.456675374},
{"learn":[1089.305345],"iteration":10,"passed_time":0.07731931723,"remaining_time":1.328486451},
{"learn":[1077.654241],"iteration":11,"passed_time":0.07840940613,"remaining_time":1.228414029},
{"learn":[1066.36799],"iteration":12,"passed_time":0.0797289262,"remaining_time":1.146869938},
{"learn":[1056.45487],"iteration":13,"passed_time":0.08082190938,"remaining_time":1.073776796},
{"learn":[1049.719503],"iteration":14,"passed_time":0.08141196839,"remaining_time":1.004080943},
{"learn":[1040.964075],"iteration":15,"passed_time":0.0830535557,"remaining_time":0.9551158906},
{"learn":[1031.022323],"iteration":16,"passed_time":0.08421138065,"remaining_time":0.9065107447},
{"learn":[1019.405599],"iteration":17,"passed_time":0.08521131975,"remaining_time":0.8615811219},
{"learn":[1008.802654],"iteration":18,"passed_time":0.08617816127,"remaining_time":0.8209603784},
{"learn":[998.8765033],"iteration":19,"passed_time":0.087129415,"remaining_time":0.784164735},
{"learn":[989.9222324],"iteration":20,"passed_time":0.08850921579,"remaining_time":0.7544356965},
{"learn":[982.128827],"iteration":21,"passed_time":0.08952622802,"remaining_time":0.7243485722},
{"learn":[972.9494737],"iteration":22,"passed_time":0.09053102073,"remaining_time":0.6966952465},
{"learn":[964.4267973],"iteration":23,"passed_time":0.09150941766,"remaining_time":0.6710690629},
{"learn":[955.4031073],"iteration":24,"passed_time":0.09266493518,"remaining_time":0.6486545462},
{"learn":[946.9462415],"iteration":25,"passed_time":0.09384064841,"remaining_time":0.6280104932},
{"learn":[940.5060191],"iteration":26,"passed_time":0.09487017445,"remaining_time":0.6078718585},
{"learn":[934.1656381],"iteration":27,"passed_time":0.09594190629,"remaining_time":0.5893574243},
{"learn":[928.2015012],"iteration":28,"passed_time":0.09715513752,"remaining_time":0.5728802936},
{"learn":[922.2344078],"iteration":29,"passed_time":0.09826577025,"remaining_time":0.5568393647},
{"learn":[916.8781557],"iteration":30,"passed_time":0.09924976563,"remaining_time":0.541071303},
{"learn":[909.1612595],"iteration":31,"passed_time":0.1004310079,"remaining_time":0.5272627913},
{"learn":[902.7336359],"iteration":32,"passed_time":0.1015177702,"remaining_time":0.5137414429},
{"learn":[897.3643638],"iteration":33,"passed_time":0.1026955278,"remaining_time":0.5013958122},
{"learn":[892.3304279],"iteration":34,"passed_time":0.1036299584,"remaining_time":0.4885412325},
{"learn":[887.2352565],"iteration":35,"passed_time":0.1048837469,"remaining_time":0.4778037359},
{"learn":[882.4097654],"iteration":36,"passed_time":0.105702724,"remaining_time":0.4656633518},
{"learn":[877.8507761],"iteration":37,"passed_time":0.1066921147,"remaining_time":0.4548453312},
{"learn":[872.9284817],"iteration":38,"passed_time":0.1079352515,"remaining_time":0.4455788587},
{"learn":[868.5593887],"iteration":39,"passed_time":0.1090077221,"remaining_time":0.4360308883},
{"learn":[863.8064775],"iteration":40,"passed_time":0.110216901,"remaining_time":0.4274265184},
{"learn":[858.6853071],"iteration":41,"passed_time":0.1113940865,"remaining_time":0.4190539446},
{"learn":[854.098875],"iteration":42,"passed_time":0.1126054678,"remaining_time":0.4111408941},
{"learn":[849.9817535],"iteration":43,"passed_time":0.1138686336,"remaining_time":0.4037160647},
{"learn":[845.0035108],"iteration":44,"passed_time":0.1149596323,"remaining_time":0.3959720668},
{"learn":[840.5960222],"iteration":45,"passed_time":0.1162419608,"remaining_time":0.3891578687},
{"learn":[837.1365665],"iteration":46,"passed_time":0.1174746907,"remaining_time":0.38241761},
{"learn":[831.9101313],"iteration":47,"passed_time":0.1183556865,"remaining_time":0.3747930071},
{"learn":[827.4261101],"iteration":48,"passed_time":0.1195752289,"remaining_time":0.3684869298},
{"learn":[823.0178757],"iteration":49,"passed_time":0.1207532339,"remaining_time":0.3622597017},
{"learn":[819.5027268],"iteration":50,"passed_time":0.121709435,"remaining_time":0.355582467},
{"learn":[815.9280446],"iteration":51,"passed_time":0.1229410068,"remaining_time":0.3499090194},
{"learn":[811.3674862],"iteration":52,"passed_time":0.1240900361,"remaining_time":0.3441742509},
{"learn":[807.5581445],"iteration":53,"passed_time":0.1253816099,"remaining_time":0.3389947231},
{"learn":[805.1350772],"iteration":54,"passed_time":0.126863412,"remaining_time":0.3344580861},
{"learn":[801.536756],"iteration":55,"passed_time":0.1279573362,"remaining_time":0.3290331501},
{"learn":[798.4727673],"iteration":56,"passed_time":0.1296366897,"remaining_time":0.3252288883},
{"learn":[795.6118055],"iteration":57,"passed_time":0.1312492344,"remaining_time":0.3213343326},
{"learn":[792.0874742],"iteration":58,"passed_time":0.1324514589,"remaining_time":0.3165365373},
{"learn":[788.6521042],"iteration":59,"passed_time":0.1334912321,"remaining_time":0.3114795416},
{"learn":[786.0031458],"iteration":60,"passed_time":0.1351696056,"remaining_time":0.3080094291},
{"learn":[783.3846374],"iteration":61,"passed_time":0.1365643058,"remaining_time":0.3039657128},
{"learn":[780.6336085],"iteration":62,"passed_time":0.1376834607,"remaining_time":0.2994068908},
{"learn":[778.3117441],"iteration":63,"passed_time":0.1390584548,"remaining_time":0.2954992165},
{"learn":[775.8943612],"iteration":64,"passed_time":0.1401704453,"remaining_time":0.2911232325},
{"learn":[772.2036935],"iteration":65,"passed_time":0.1416238809,"remaining_time":0.2875393946},
{"learn":[770.0234989],"iteration":66,"passed_time":0.142870985,"remaining_time":0.2836095671},
{"learn":[768.3518369],"iteration":67,"passed_time":0.1440166885,"remaining_time":0.279561807},
{"learn":[765.002201],"iteration":68,"passed_time":0.145502805,"remaining_time":0.2762444559},
{"learn":[763.0533241],"iteration":69,"passed_time":0.1466335545,"remaining_time":0.2723194583},
{"learn":[759.9361755],"iteration":70,"passed_time":0.1480940001,"remaining_time":0.2690721974},
{"learn":[758.1289795],"iteration":71,"passed_time":0.1490124766,"remaining_time":0.2649110695},
{"learn":[755.8712733],"iteration":72,"passed_time":0.1504003144,"remaining_time":0.2616553414},
{"learn":[754.8291504],"iteration":73,"passed_time":0.1514026495,"remaining_time":0.2577937004},
{"learn":[752.8554299],"iteration":74,"passed_time":0.1523067405,"remaining_time":0.2538445675},
{"learn":[750.1431579],"iteration":75,"passed_time":0.153589694,"remaining_time":0.2505937113},
{"learn":[748.4145936],"iteration":76,"passed_time":0.1546974776,"remaining_time":0.2471141525},
{"learn":[747.2053946],"iteration":77,"passed_time":0.1558751484,"remaining_time":0.2438047193},
{"learn":[745.6027484],"iteration":78,"passed_time":0.1571476829,"remaining_time":0.2406945523},
{"learn":[742.2815023],"iteration":79,"passed_time":0.1583849677,"remaining_time":0.2375774516},
{"learn":[740.8296552],"iteration":80,"passed_time":0.159488883,"remaining_time":0.2343108281},
{"learn":[739.0842796],"iteration":81,"passed_time":0.1602516743,"remaining_time":0.2306060679},
{"learn":[737.5147133],"iteration":82,"passed_time":0.1616264904,"remaining_time":0.2278349322},
{"learn":[736.6884212],"iteration":83,"passed_time":0.1630838187,"remaining_time":0.2252109877},
{"learn":[735.7147397],"iteration":84,"passed_time":0.1643932964,"remaining_time":0.2224144599},
{"learn":[734.6473005],"iteration":85,"passed_time":0.1656920261,"remaining_time":0.2196382672},
{"learn":[732.5771504],"iteration":86,"passed_time":0.1665841911,"remaining_time":0.2163679723},
{"learn":[731.7295064],"iteration":87,"passed_time":0.1677123527,"remaining_time":0.2134520852},
{"learn":[730.0542917],"iteration":88,"passed_time":0.1690111206,"remaining_time":0.2107891504},
{"learn":[729.4143551],"iteration":89,"passed_time":0.1701930113,"remaining_time":0.2080136804},
{"learn":[727.8891217],"iteration":90,"passed_time":0.1711442346,"remaining_time":0.2049969404},
{"learn":[726.9765162],"iteration":91,"passed_time":0.1722283075,"remaining_time":0.2021810566},
{"learn":[725.7303467],"iteration":92,"passed_time":0.1732149584,"remaining_time":0.1992903285},
{"learn":[724.3797265],"iteration":93,"passed_time":0.1746621689,"remaining_time":0.196959467},
{"learn":[723.1763474],"iteration":94,"passed_time":0.1758426836,"remaining_time":0.1943524398},
{"learn":[722.3543542],"iteration":95,"passed_time":0.1771968092,"remaining_time":0.19196321},
{"learn":[721.2594616],"iteration":96,"passed_time":0.1784433472,"remaining_time":0.18948108},
{"learn":[719.6482295],"iteration":97,"passed_time":0.1797881198,"remaining_time":0.1871264104},
{"learn":[718.5175243],"iteration":98,"passed_time":0.1812806942,"remaining_time":0.1849429304},
{"learn":[716.4264582],"iteration":99,"passed_time":0.1834067696,"remaining_time":0.1834067696},
{"learn":[714.7417896],"iteration":100,"passed_time":0.1851306017,"remaining_time":0.1814646492},
{"learn":[713.6614177],"iteration":101,"passed_time":0.1863252458,"remaining_time":0.1790183734},
{"learn":[711.5251525],"iteration":102,"passed_time":0.1877203262,"remaining_time":0.1767851616},
{"learn":[710.0803614],"iteration":103,"passed_time":0.1891408605,"remaining_time":0.1745915635},
{"learn":[709.5886346],"iteration":104,"passed_time":0.1898306168,"remaining_time":0.1717515104},
{"learn":[708.9465534],"iteration":105,"passed_time":0.1910021205,"remaining_time":0.169379239},
{"learn":[708.4183154],"iteration":106,"passed_time":0.192253362,"remaining_time":0.1670987165},
{"learn":[707.2804273],"iteration":107,"passed_time":0.1940152269,"remaining_time":0.1652722303},
{"learn":[706.3323875],"iteration":108,"passed_time":0.1953771177,"remaining_time":0.1631130065},
{"learn":[704.4670105],"iteration":109,"passed_time":0.1971166747,"remaining_time":0.1612772793},
{"learn":[704.3624372],"iteration":110,"passed_time":0.1975177539,"remaining_time":0.158370091},
{"learn":[703.6331897],"iteration":111,"passed_time":0.1988799451,"remaining_time":0.156262814},
{"learn":[703.0892331],"iteration":112,"passed_time":0.2001270205,"remaining_time":0.1540800954},
{"learn":[700.7039505],"iteration":113,"passed_time":0.2012959399,"remaining_time":0.1518548318},
{"learn":[699.8249946],"iteration":114,"passed_time":0.2023463405,"remaining_time":0.1495603386},
{"learn":[699.4200944],"iteration":115,"passed_time":0.203639095,"remaining_time":0.1474627929},
{"learn":[698.433819],"iteration":116,"passed_time":0.2055772097,"remaining_time":0.145836824},
{"learn":[697.7781811],"iteration":117,"passed_time":0.2065951482,"remaining_time":0.14356612},
{"learn":[697.3934238],"iteration":118,"passed_time":0.2072683696,"remaining_time":0.1410818314},
{"learn":[695.6964032],"iteration":119,"passed_time":0.2082741676,"remaining_time":0.1388494451},
{"learn":[694.9885252],"iteration":120,"passed_time":0.2094239078,"remaining_time":0.1367313117},
{"learn":[693.7946004],"iteration":121,"passed_time":0.2107005745,"remaining_time":0.1347102034},
{"learn":[693.3391353],"iteration":122,"passed_time":0.2121465913,"remaining_time":0.1328072157},
{"learn":[692.9340296],"iteration":123,"passed_time":0.2132604195,"remaining_time":0.1307079991},
{"learn":[692.3126465],"iteration":124,"passed_time":0.2144828493,"remaining_time":0.1286897096},
{"learn":[691.8662754],"iteration":125,"passed_time":0.2158096858,"remaining_time":0.126745371},
{"learn":[690.6114549],"iteration":126,"passed_time":0.2172435039,"remaining_time":0.1248722503},
{"learn":[690.2034703],"iteration":127,"passed_time":0.2185503695,"remaining_time":0.1229345828},
{"learn":[689.7707662],"iteration":128,"passed_time":0.2199245067,"remaining_time":0.1210437208},
{"learn":[689.0564172],"iteration":129,"passed_time":0.2212985693,"remaining_time":0.1191607681},
{"learn":[687.717346],"iteration":130,"passed_time":0.2223286718,"remaining_time":0.1171044149},
{"learn":[686.9204134],"iteration":131,"passed_time":0.2234730315,"remaining_time":0.1151224708},
{"learn":[686.7312104],"iteration":132,"passed_time":0.2241643313,"remaining_time":0.1129248887},
{"learn":[685.7718803],"iteration":133,"passed_time":0.225442386,"remaining_time":0.1110387872},
{"learn":[685.1559092],"iteration":134,"passed_time":0.2266883476,"remaining_time":0.1091462415},
{"learn":[684.562426],"iteration":135,"passed_time":0.228055981,"remaining_time":0.1073204616},
{"learn":[684.1862169],"iteration":136,"passed_time":0.2295718138,"remaining_time":0.1055695202},
{"learn":[682.6384395],"iteration":137,"passed_time":0.2307984877,"remaining_time":0.1036920742},
{"learn":[681.9689383],"iteration":138,"passed_time":0.2320731604,"remaining_time":0.101845056},
{"learn":[681.6950726],"iteration":139,"passed_time":0.2330357881,"remaining_time":0.0998724806},
{"learn":[681.1421015],"iteration":140,"passed_time":0.2340149793,"remaining_time":0.09792116157},
{"learn":[680.3810554],"iteration":141,"passed_time":0.2354801597,"remaining_time":0.09618203704},
{"learn":[679.6499751],"iteration":142,"passed_time":0.2369857019,"remaining_time":0.09446283223},
{"learn":[679.2975238],"iteration":143,"passed_time":0.2384154876,"remaining_time":0.09271713408},
{"learn":[678.9651185],"iteration":144,"passed_time":0.2393762072,"remaining_time":0.09079787171},
{"learn":[678.5136306],"iteration":145,"passed_time":0.2404858278,"remaining_time":0.08894681301},
{"learn":[677.76526],"iteration":146,"passed_time":0.2419200417,"remaining_time":0.08722287218},
{"learn":[677.59399],"iteration":147,"passed_time":0.2430429183,"remaining_time":0.08539345777},
{"learn":[677.2432651],"iteration":148,"passed_time":0.2446863842,"remaining_time":0.08375171539},
{"learn":[676.5944743],"iteration":149,"passed_time":0.2462575452,"remaining_time":0.08208584839},
{"learn":[675.7690882],"iteration":150,"passed_time":0.247383889,"remaining_time":0.08027689112},
{"learn":[675.4062376],"iteration":151,"passed_time":0.2484719378,"remaining_time":0.07846482246},
{"learn":[674.892677],"iteration":152,"passed_time":0.2495904148,"remaining_time":0.07667156532},
{"learn":[674.1725494],"iteration":153,"passed_time":0.2506649193,"remaining_time":0.07487393695},
{"learn":[673.9772449],"iteration":154,"passed_time":0.2519890795,"remaining_time":0.07315811985},
{"learn":[673.4970453],"iteration":155,"passed_time":0.2533280678,"remaining_time":0.0714515063},
{"learn":[673.3141813],"iteration":156,"passed_time":0.2543978195,"remaining_time":0.0696758359},
{"learn":[672.9813872],"iteration":157,"passed_time":0.2555203739,"remaining_time":0.06792313738},
{"learn":[672.2015577],"iteration":158,"passed_time":0.2567433063,"remaining_time":0.0662042488},
{"learn":[671.9716404],"iteration":159,"passed_time":0.2578246889,"remaining_time":0.06445617223},
{"learn":[670.9687749],"iteration":160,"passed_time":0.2600051454,"remaining_time":0.06298261286},
{"learn":[670.6485325],"iteration":161,"passed_time":0.2609358761,"remaining_time":0.06120718082},
{"learn":[670.0470061],"iteration":162,"passed_time":0.261890262,"remaining_time":0.05944748278},
{"learn":[669.4813476],"iteration":163,"passed_time":0.2629718365,"remaining_time":0.05772552508},
{"learn":[669.0317092],"iteration":164,"passed_time":0.2639785286,"remaining_time":0.05599544546},
{"learn":[668.5773563],"iteration":165,"passed_time":0.2650613419,"remaining_time":0.05428967243},
{"learn":[667.4181285],"iteration":166,"passed_time":0.266401654,"remaining_time":0.05264224301},
{"learn":[666.5494105],"iteration":167,"passed_time":0.267350978,"remaining_time":0.0509239958},
{"learn":[666.3232865],"iteration":168,"passed_time":0.2683020164,"remaining_time":0.04921516277},
{"learn":[666.1469587],"iteration":169,"passed_time":0.269144535,"remaining_time":0.0474960944},
{"learn":[665.3959448],"iteration":170,"passed_time":0.2700700588,"remaining_time":0.04580135499},
{"learn":[664.8010985],"iteration":171,"passed_time":0.2712912558,"remaining_time":0.0441636928},
{"learn":[664.2527363],"iteration":172,"passed_time":0.2724327854,"remaining_time":0.0425184116},
{"learn":[663.7325956],"iteration":173,"passed_time":0.2735866353,"remaining_time":0.0408807616},
{"learn":[663.0232295],"iteration":174,"passed_time":0.2747740411,"remaining_time":0.03925343444},
{"learn":[662.3754284],"iteration":175,"passed_time":0.2760009077,"remaining_time":0.03763648742},
{"learn":[662.1405268],"iteration":176,"passed_time":0.2771759204,"remaining_time":0.03601721},
{"learn":[662.1402421],"iteration":177,"passed_time":0.2775301442,"remaining_time":0.0343014785},
{"learn":[661.6438968],"iteration":178,"passed_time":0.2789184577,"remaining_time":0.03272227716},
{"learn":[661.2122211],"iteration":179,"passed_time":0.2799615983,"remaining_time":0.03110684426},
{"learn":[660.5279576],"iteration":180,"passed_time":0.2812680342,"remaining_time":0.02952537376},
{"learn":[660.5106043],"iteration":181,"passed_time":0.2816160085,"remaining_time":0.02785213271},
{"learn":[659.9080617],"iteration":182,"passed_time":0.2829528439,"remaining_time":0.02628523686},
{"learn":[658.6519589],"iteration":183,"passed_time":0.2842996044,"remaining_time":0.02472170473},
{"learn":[658.3724295],"iteration":184,"passed_time":0.285267525,"remaining_time":0.02312979932},
{"learn":[657.9753153],"iteration":185,"passed_time":0.2864631318,"remaining_time":0.02156174111},
{"learn":[657.6872883],"iteration":186,"passed_time":0.2876984157,"remaining_time":0.02000042462},
{"learn":[657.6167488],"iteration":187,"passed_time":0.2888840887,"remaining_time":0.01843940992},
{"learn":[657.2902903],"iteration":188,"passed_time":0.2900142765,"remaining_time":0.01687913779},
{"learn":[656.9208801],"iteration":189,"passed_time":0.2913257284,"remaining_time":0.01533293307},
{"learn":[656.1220912],"iteration":190,"passed_time":0.2923024698,"remaining_time":0.01377341481},
{"learn":[655.6014439],"iteration":191,"passed_time":0.2936221644,"remaining_time":0.01223425685},
{"learn":[655.2552173],"iteration":192,"passed_time":0.2947231238,"remaining_time":0.01068943972},
{"learn":[654.899109],"iteration":193,"passed_time":0.2960370983,"remaining_time":0.009155786547},
{"learn":[654.028857],"iteration":194,"passed_time":0.2971749081,"remaining_time":0.00761986944},
{"learn":[653.7951562],"iteration":195,"passed_time":0.298063888,"remaining_time":0.006082936489},
{"learn":[653.447744],"iteration":196,"passed_time":0.299478052,"remaining_time":0.004560579473},
{"learn":[652.3318516],"iteration":197,"passed_time":0.3006719817,"remaining_time":0.003037090724},
{"learn":[651.663035],"iteration":198,"passed_time":0.3018584743,"remaining_time":0.001516876755},
{"learn":[651.0690553],"iteration":199,"passed_time":0.3029690827,"remaining_time":0}
]}